email_typo_fixer/__init__.py
email_typo_fixer/email_typo_fixer.py
email_typo_fixer-1.1.3.dist-info/LICENSE
email_typo_fixer-1.1.3.dist-info/METADATA
email_typo_fixer-1.1.3.dist-info/WHEEL
email_typo_fixer-1.1.3.dist-info/RECORD
