Metadata-Version: 2.3
Name: email-typo-fixer
Version: 1.1.3
Summary: A Python library to automatically detect and fix common typos in email addresses
License: MIT
Keywords: email,typo,correction,validation,normalization
Author: Joao Brito
Requires-Python: >=3.11,<3.15
Classifier: Development Status :: 5 - Production/Stable
Classifier: Intended Audience :: Developers
Classifier: License :: OSI Approved :: MIT License
Classifier: Operating System :: OS Independent
Classifier: Programming Language :: Python :: 3
Classifier: Programming Language :: Python :: 3.11
Classifier: Programming Language :: Python :: 3.12
Classifier: Programming Language :: Python :: 3.13
Classifier: Programming Language :: Python :: 3.14
Classifier: Topic :: Communications :: Email
Classifier: Topic :: Software Development :: Libraries :: Python Modules
Classifier: Topic :: Text Processing
Requires-Dist: publicsuffixlist (>=1.0.2.20250802,<2.0.0.0)
Requires-Dist: rapidfuzz (>=3.13.0,<4.0.0)
Project-URL: Homepage, https://github.com/machado000/email-typo-fixer
Project-URL: Issues, https://github.com/machado000/email-typo-fixer/issues
